{"cameraMode":{"drawMode":0,"name":"Shaded","section":"Shading Mode"},"sceneLighting":true,"audioPlay":false,"sceneViewState":{"showFog":true,"showMaterialUpdate":false,"showSkybox":true,"showFlares":true,"showImageEffects":true,"showParticleSystems":true,"showVisualEffectGraphs":true,"m_FxEnabled":true},"in2DMode":false,"pivot":{"x":-86.15776824951172,"y":-98.28919982910156,"z":-0.6168003082275391},"rotation":{"x":-0.27971258759498598,"y":0.6696712374687195,"z":-0.303344190120697,"w":-0.6175007820129395},"size":75.406494140625,"orthographic":false}